odoo/addons/project_parent_task_filter/README.rst
odoo/addons/project_parent_task_filter/__init__.py
odoo/addons/project_parent_task_filter/__manifest__.py
odoo/addons/project_parent_task_filter/data/res_config_data.xml
odoo/addons/project_parent_task_filter/i18n/de.po
odoo/addons/project_parent_task_filter/i18n/es.po
odoo/addons/project_parent_task_filter/i18n/es_ES.po
odoo/addons/project_parent_task_filter/i18n/fr.po
odoo/addons/project_parent_task_filter/i18n/hr.po
odoo/addons/project_parent_task_filter/i18n/it.po
odoo/addons/project_parent_task_filter/i18n/project_parent_task_filter.pot
odoo/addons/project_parent_task_filter/i18n/pt.po
odoo/addons/project_parent_task_filter/i18n/sl.po
odoo/addons/project_parent_task_filter/readme/CONTRIBUTORS.rst
odoo/addons/project_parent_task_filter/readme/DESCRIPTION.rst
odoo/addons/project_parent_task_filter/readme/ROADMAP.rst
odoo/addons/project_parent_task_filter/readme/USAGE.rst
odoo/addons/project_parent_task_filter/static/description/icon.png
odoo/addons/project_parent_task_filter/static/description/index.html
odoo/addons/project_parent_task_filter/views/project_task.xml
odoo12_addon_project_parent_task_filter-12.0.1.3.0.dist-info/METADATA
odoo12_addon_project_parent_task_filter-12.0.1.3.0.dist-info/WHEEL
odoo12_addon_project_parent_task_filter-12.0.1.3.0.dist-info/top_level.txt
odoo12_addon_project_parent_task_filter-12.0.1.3.0.dist-info/RECORD
