Metadata-Version: 2.1
Name: odoo12-addon-project-parent-task-filter
Version: 12.0.1.3.0
Summary: Add a filter to show the parent tasks
Home-page: https://github.com/OCA/project
Author: C2i Change 2 improve, Odoo Community Association (OCA)
Author-email: support@odoo-community.org
License: AGPL-3
Platform: UNKNOWN
Classifier: Programming Language :: Python
Classifier: Framework :: Odoo
Classifier: License :: OSI Approved :: GNU Affero General Public License v3
Requires-Python: >=3.5
Requires-Dist: odoo (<12.1dev,>=12.0a)
